gamest/.pylintrc
gamest/__init__.py
gamest/app.py
gamest/db.py
gamest/errors.py
gamest/icon.png
gamest/icon.svg
gamest/launcher.py
gamest/plugins.py
gamest/util.py
gamest_plugins/play_session_notifier/__init__.py
gamest_plugins/play_session_notifier/module.py
gamest_plugins/process_identifier/__init__.py
gamest_plugins/process_identifier/module.py
gamest-4.1.8.dist-info/COPYING
gamest-4.1.8.dist-info/METADATA
gamest-4.1.8.dist-info/WHEEL
gamest-4.1.8.dist-info/entry_points.txt
gamest-4.1.8.dist-info/top_level.txt
gamest-4.1.8.dist-info/RECORD
