Metadata-Version: 2.1
Name: gamest
Version: 4.1.8
Summary: Tracks game play time.
Home-page: https://github.com/sopoforic/gamest
Author: Tracy Poff
Author-email: tracy.poff@gmail.com
Classifier: Development Status :: 4 - Beta
Classifier: Environment :: Win32 (MS Windows)
Classifier: Intended Audience :: End Users/Desktop
Classifier: License :: OSI Approved :: GNU General Public License v3 or later (GPLv3+)
Classifier: Programming Language :: Python :: 3
Classifier: Topic :: Games/Entertainment
License-File: COPYING
Requires-Dist: appdirs
Requires-Dist: psutil >=5.7.0
Requires-Dist: requests
Requires-Dist: sqlalchemy
